mlflow_watsonml/__init__.py
mlflow_watsonml/_version.py
mlflow_watsonml/config.py
mlflow_watsonml/deploy.py
mlflow_watsonml/logging.py
mlflow_watsonml/store.py
mlflow_watsonml/utils.py
mlflow_watsonml/wml.py
mlflow_watsonml-0.11.4.dist-info/LICENSE
mlflow_watsonml-0.11.4.dist-info/METADATA
mlflow_watsonml-0.11.4.dist-info/WHEEL
mlflow_watsonml-0.11.4.dist-info/entry_points.txt
mlflow_watsonml-0.11.4.dist-info/top_level.txt
mlflow_watsonml-0.11.4.dist-info/RECORD
