Metadata-Version: 2.1
Name: mlflow-watsonml
Version: 0.11.4
Summary: WatsonML MLflow deployment plugin
Home-page: https://github.com/IBM/mlflow-watsonml
Author: IBM AI Model Factory team
Author-email: dhruv.shah@ibm.com
Requires-Python: >=3.9
License-File: LICENSE
Requires-Dist: ibm-watson-machine-learning ==1.0.327
Requires-Dist: mlflow >=2.6.0
Requires-Dist: python-dotenv ~=1.0.0
Requires-Dist: boto3 >=1.24.59
Provides-Extra: dev
Requires-Dist: ipython ; extra == 'dev'
Requires-Dist: black ; extra == 'dev'
Requires-Dist: pytest ; extra == 'dev'
Requires-Dist: build ; extra == 'dev'
Requires-Dist: wheel ; extra == 'dev'
Requires-Dist: twine ; extra == 'dev'
Requires-Dist: pytest-cov ; extra == 'dev'
Provides-Extra: docs
Requires-Dist: mkdocs ; extra == 'docs'
Requires-Dist: mkdocstrings-python ; extra == 'docs'
Requires-Dist: mkdocs-material ; extra == 'docs'
Provides-Extra: onnx
Requires-Dist: onnx ; extra == 'onnx'
Requires-Dist: onnxruntime ; extra == 'onnx'
